[
  {
    "time": 1389140100,
    "kw": 0.3
  },
  {
    "time": 1389141000,
    "kw": 0.28
  },
  {
    "time": 1389141900,
    "kw": 0.3
  },
  {
    "time": 1389142800,
    "kw": 0.32
  },
  {
    "time": 1389143700,
    "kw": 0.29
  },
  {
    "time": 1389144600,
    "kw": 0.13
  },
  {
    "time": 1389145500,
    "kw": 0.09
  },
  {
    "time": 1389146400,
    "kw": 0.08
  },
  {
    "time": 1389147300,
    "kw": 0.07
  },
  {
    "time": 1389148200,
    "kw": 0.05
  },
  {
    "time": 1389149100,
    "kw": 0.08
  },
  {
    "time": 1389150000,
    "kw": 0.07
  },
  {
    "time": 1389150900,
    "kw": 0.06
  },
  {
    "time": 1389151800,
    "kw": 0.07
  },
  {
    "time": 1389152700,
    "kw": 0.07
  },
  {
    "time": 1389153600,
    "kw": 0.07
  },
  {
    "time": 1389154500,
    "kw": 0.05
  },
  {
    "time": 1389155400,
    "kw": 0.04
  },
  {
    "time": 1389156300,
    "kw": 0.28
  },
  {
    "time": 1389157200,
    "kw": 0.32
  },
  {
    "time": 1389158100,
    "kw": 0.28
  },
  {
    "time": 1389159000,
    "kw": 0.29
  },
  {
    "time": 1389159900,
    "kw": 0.39
  },
  {
    "time": 1389160800,
    "kw": 0.37
  },
  {
    "time": 1389161700,
    "kw": 0.36
  },
  {
    "time": 1389162600,
    "kw": 0.37
  },
  {
    "time": 1389163500,
    "kw": 0.39
  },
  {
    "time": 1389164400,
    "kw": 0.39
  },
  {
    "time": 1389165300,
    "kw": 0.35
  },
  {
    "time": 1389166200,
    "kw": 0.14
  },
  {
    "time": 1389167100,
    "kw": 0.15
  },
  {
    "time": 1389168000,
    "kw": 0.13
  },
  {
    "time": 1389168900,
    "kw": 0.12
  },
  {
    "time": 1389169800,
    "kw": 0.12
  },
  {
    "time": 1389170700,
    "kw": 0.13
  },
  {
    "time": 1389171600,
    "kw": 0.14
  },
  {
    "time": 1389172500,
    "kw": 0.12
  },
  {
    "time": 1389173400,
    "kw": 0.11
  },
  {
    "time": 1389174300,
    "kw": 0.13
  },
  {
    "time": 1389175200,
    "kw": 0.14
  },
  {
    "time": 1389176100,
    "kw": 0.12
  },
  {
    "time": 1389177000,
    "kw": 0.12
  },
  {
    "time": 1389177900,
    "kw": 0.14
  },
  {
    "time": 1389178800,
    "kw": 0.14
  },
  {
    "time": 1389179700,
    "kw": 0.11
  },
  {
    "time": 1389180600,
    "kw": 0.11
  },
  {
    "time": 1389181500,
    "kw": 0.16
  },
  {
    "time": 1389182400,
    "kw": 0.14
  },
  {
    "time": 1389183300,
    "kw": 0.12
  },
  {
    "time": 1389184200,
    "kw": 0.3
  },
  {
    "time": 1389185100,
    "kw": 0.44
  },
  {
    "time": 1389186000,
    "kw": 0.91
  },
  {
    "time": 1389186900,
    "kw": 0.97
  },
  {
    "time": 1389187800,
    "kw": 0.95
  },
  {
    "time": 1389188700,
    "kw": 0.93
  },
  {
    "time": 1389189600,
    "kw": 1.02
  },
  {
    "time": 1389190500,
    "kw": 1.01
  },
  {
    "time": 1389191400,
    "kw": 1.18
  },
  {
    "time": 1389192300,
    "kw": 1.1
  },
  {
    "time": 1389193200,
    "kw": 0.98
  },
  {
    "time": 1389194100,
    "kw": 0.98
  },
  {
    "time": 1389195000,
    "kw": 0.98
  },
  {
    "time": 1389195900,
    "kw": 1
  },
  {
    "time": 1389196800,
    "kw": 0.96
  },
  {
    "time": 1389197700,
    "kw": 0.97
  },
  {
    "time": 1389198600,
    "kw": 0.99
  },
  {
    "time": 1389199500,
    "kw": 0.97
  },
  {
    "time": 1389200400,
    "kw": 1.2
  },
  {
    "time": 1389201300,
    "kw": 1.32
  },
  {
    "time": 1389202200,
    "kw": 1.25
  },
  {
    "time": 1389203100,
    "kw": 1.18
  },
  {
    "time": 1389204000,
    "kw": 1.12
  },
  {
    "time": 1389204900,
    "kw": 1.12
  },
  {
    "time": 1389205800,
    "kw": 1.54
  },
  {
    "time": 1389206700,
    "kw": 0.75
  },
  {
    "time": 1389207600,
    "kw": 0.3
  },
  {
    "time": 1389208500,
    "kw": 0.18
  },
  {
    "time": 1389209400,
    "kw": 0.24
  },
  {
    "time": 1389210300,
    "kw": 0.18
  },
  {
    "time": 1389211200,
    "kw": 0.16
  },
  {
    "time": 1389212100,
    "kw": 0.13
  },
  {
    "time": 1389213000,
    "kw": 0.35
  },
  {
    "time": 1389213900,
    "kw": 0.24
  },
  {
    "time": 1389214800,
    "kw": 0.17
  },
  {
    "time": 1389215700,
    "kw": 0.13
  },
  {
    "time": 1389216600,
    "kw": 0.14
  },
  {
    "time": 1389217500,
    "kw": 0.13
  },
  {
    "time": 1389218400,
    "kw": 0.06
  },
  {
    "time": 1389219300,
    "kw": 0.05
  },
  {
    "time": 1389220200,
    "kw": 0.05
  },
  {
    "time": 1389221100,
    "kw": 0.06
  },
  {
    "time": 1389222000,
    "kw": 0.06
  },
  {
    "time": 1389222900,
    "kw": 0.08
  },
  {
    "time": 1389223800,
    "kw": 0.05
  },
  {
    "time": 1389224700,
    "kw": 0.05
  },
  {
    "time": 1389225600,
    "kw": 0.06
  },
  {
    "time": 1389226500,
    "kw": 0.06
  },
  {
    "time": 1389227400,
    "kw": 0.06
  },
  {
    "time": 1389228300,
    "kw": 0.07
  },
  {
    "time": 1389229200,
    "kw": 0.2
  },
  {
    "time": 1389230100,
    "kw": 0.33
  },
  {
    "time": 1389231000,
    "kw": 0.28
  },
  {
    "time": 1389231900,
    "kw": 0.28
  },
  {
    "time": 1389232800,
    "kw": 0.26
  },
  {
    "time": 1389233700,
    "kw": 0.26
  },
  {
    "time": 1389234600,
    "kw": 0.28
  },
  {
    "time": 1389235500,
    "kw": 0.3
  },
  {
    "time": 1389236400,
    "kw": 0.28
  },
  {
    "time": 1389237300,
    "kw": 0.28
  },
  {
    "time": 1389238200,
    "kw": 0.3
  },
  {
    "time": 1389239100,
    "kw": 0.29
  },
  {
    "time": 1389240000,
    "kw": 0.12
  },
  {
    "time": 1389240900,
    "kw": 0.07
  },
  {
    "time": 1389241800,
    "kw": 0.06
  },
  {
    "time": 1389242700,
    "kw": 0.06
  },
  {
    "time": 1389243600,
    "kw": 0.06
  },
  {
    "time": 1389244500,
    "kw": 0.15
  },
  {
    "time": 1389245400,
    "kw": 0.08
  },
  {
    "time": 1389246300,
    "kw": 0.12
  },
  {
    "time": 1389247200,
    "kw": 0.28
  },
  {
    "time": 1389248100,
    "kw": 0.13
  },
  {
    "time": 1389249000,
    "kw": 0.14
  },
  {
    "time": 1389249900,
    "kw": 0.21
  },
  {
    "time": 1389250800,
    "kw": 0.15
  },
  {
    "time": 1389251700,
    "kw": 0.26
  },
  {
    "time": 1389252600,
    "kw": 0.96
  },
  {
    "time": 1389253500,
    "kw": 0.97
  },
  {
    "time": 1389254400,
    "kw": 0.95
  },
  {
    "time": 1389255300,
    "kw": 1.08
  },
  {
    "time": 1389256200,
    "kw": 1.22
  },
  {
    "time": 1389257100,
    "kw": 0.95
  },
  {
    "time": 1389258000,
    "kw": 0.94
  },
  {
    "time": 1389258900,
    "kw": 1.25
  },
  {
    "time": 1389259800,
    "kw": 1
  },
  {
    "time": 1389260700,
    "kw": 0.94
  },
  {
    "time": 1389261600,
    "kw": 0.97
  },
  {
    "time": 1389262500,
    "kw": 0.95
  },
  {
    "time": 1389263400,
    "kw": 0.94
  },
  {
    "time": 1389264300,
    "kw": 0.93
  },
  {
    "time": 1389265200,
    "kw": 0.91
  },
  {
    "time": 1389266100,
    "kw": 0.89
  },
  {
    "time": 1389267000,
    "kw": 0.9
  },
  {
    "time": 1389267900,
    "kw": 0.9
  },
  {
    "time": 1389268800,
    "kw": 0.91
  },
  {
    "time": 1389269700,
    "kw": 0.84
  },
  {
    "time": 1389270600,
    "kw": 0.14
  },
  {
    "time": 1389271500,
    "kw": 0.11
  },
  {
    "time": 1389272400,
    "kw": 0.12
  },
  {
    "time": 1389273300,
    "kw": 0.14
  },
  {
    "time": 1389274200,
    "kw": 0.26
  },
  {
    "time": 1389275100,
    "kw": 0.92
  },
  {
    "time": 1389276000,
    "kw": 0.91
  },
  {
    "time": 1389276900,
    "kw": 0.91
  },
  {
    "time": 1389277800,
    "kw": 0.93
  },
  {
    "time": 1389278700,
    "kw": 0.91
  },
  {
    "time": 1389279600,
    "kw": 0.9
  },
  {
    "time": 1389280500,
    "kw": 0.9
  },
  {
    "time": 1389281400,
    "kw": 0.91
  },
  {
    "time": 1389282300,
    "kw": 1.19
  },
  {
    "time": 1389283200,
    "kw": 1.54
  },
  {
    "time": 1389284100,
    "kw": 1.25
  },
  {
    "time": 1389285000,
    "kw": 1.19
  },
  {
    "time": 1389285900,
    "kw": 1.21
  },
  {
    "time": 1389286800,
    "kw": 1.22
  },
  {
    "time": 1389287700,
    "kw": 1.21
  },
  {
    "time": 1389288600,
    "kw": 1.2
  },
  {
    "time": 1389289500,
    "kw": 1.66
  },
  {
    "time": 1389290400,
    "kw": 1.47
  },
  {
    "time": 1389291300,
    "kw": 1.22
  },
  {
    "time": 1389292200,
    "kw": 1.14
  },
  {
    "time": 1389293100,
    "kw": 0.64
  },
  {
    "time": 1389294000,
    "kw": 0.19
  },
  {
    "time": 1389294900,
    "kw": 0.56
  },
  {
    "time": 1389295800,
    "kw": 0.21
  },
  {
    "time": 1389296700,
    "kw": 0.22
  },
  {
    "time": 1389297600,
    "kw": 0.48
  },
  {
    "time": 1389298500,
    "kw": 0.52
  },
  {
    "time": 1389299400,
    "kw": 0.28
  },
  {
    "time": 1389300300,
    "kw": 0.35
  },
  {
    "time": 1389301200,
    "kw": 0.42
  },
  {
    "time": 1389302100,
    "kw": 0.15
  },
  {
    "time": 1389303000,
    "kw": 0.17
  },
  {
    "time": 1389303900,
    "kw": 0.15
  },
  {
    "time": 1389304800,
    "kw": 0.08
  },
  {
    "time": 1389305700,
    "kw": 0.1
  },
  {
    "time": 1389306600,
    "kw": 0.09
  },
  {
    "time": 1389307500,
    "kw": 0.08
  },
  {
    "time": 1389308400,
    "kw": 0.09
  },
  {
    "time": 1389309300,
    "kw": 0.1
  },
  {
    "time": 1389310200,
    "kw": 0.09
  },
  {
    "time": 1389311100,
    "kw": 0.13
  },
  {
    "time": 1389312000,
    "kw": 0.38
  },
  {
    "time": 1389312900,
    "kw": 0.29
  },
  {
    "time": 1389313800,
    "kw": 0.21
  },
  {
    "time": 1389314700,
    "kw": 0.08
  },
  {
    "time": 1389315600,
    "kw": 0.07
  },
  {
    "time": 1389316500,
    "kw": 0.08
  },
  {
    "time": 1389317400,
    "kw": 0.08
  },
  {
    "time": 1389318300,
    "kw": 0.05
  },
  {
    "time": 1389319200,
    "kw": 0.05
  },
  {
    "time": 1389320100,
    "kw": 0.06
  },
  {
    "time": 1389321000,
    "kw": 0.06
  },
  {
    "time": 1389321900,
    "kw": 0.04
  },
  {
    "time": 1389322800,
    "kw": 0.06
  },
  {
    "time": 1389323700,
    "kw": 0.09
  },
  {
    "time": 1389324600,
    "kw": 0.08
  },
  {
    "time": 1389325500,
    "kw": 0.06
  },
  {
    "time": 1389326400,
    "kw": 0.29
  },
  {
    "time": 1389327300,
    "kw": 0.19
  },
  {
    "time": 1389328200,
    "kw": 0.08
  },
  {
    "time": 1389329100,
    "kw": 0.06
  },
  {
    "time": 1389330000,
    "kw": 0.05
  },
  {
    "time": 1389330900,
    "kw": 0.07
  },
  {
    "time": 1389331800,
    "kw": 0.08
  },
  {
    "time": 1389332700,
    "kw": 0.15
  },
  {
    "time": 1389333600,
    "kw": 0.16
  },
  {
    "time": 1389334500,
    "kw": 0.15
  },
  {
    "time": 1389335400,
    "kw": 0.16
  },
  {
    "time": 1389336300,
    "kw": 0.14
  },
  {
    "time": 1389337200,
    "kw": 0.15
  },
  {
    "time": 1389338100,
    "kw": 0.19
  },
  {
    "time": 1389339000,
    "kw": 0.98
  },
  {
    "time": 1389339900,
    "kw": 0.95
  },
  {
    "time": 1389340800,
    "kw": 0.94
  },
  {
    "time": 1389341700,
    "kw": 0.93
  },
  {
    "time": 1389342600,
    "kw": 0.93
  },
  {
    "time": 1389343500,
    "kw": 0.92
  },
  {
    "time": 1389344400,
    "kw": 0.93
  },
  {
    "time": 1389345300,
    "kw": 0.95
  },
  {
    "time": 1389346200,
    "kw": 0.94
  },
  {
    "time": 1389347100,
    "kw": 0.95
  },
  {
    "time": 1389348000,
    "kw": 0.95
  },
  {
    "time": 1389348900,
    "kw": 1.28
  },
  {
    "time": 1389349800,
    "kw": 1.1
  },
  {
    "time": 1389350700,
    "kw": 0.99
  },
  {
    "time": 1389351600,
    "kw": 0.95
  },
  {
    "time": 1389352500,
    "kw": 0.96
  },
  {
    "time": 1389353400,
    "kw": 0.95
  },
  {
    "time": 1389354300,
    "kw": 0.96
  },
  {
    "time": 1389355200,
    "kw": 0.96
  },
  {
    "time": 1389356100,
    "kw": 0.22
  },
  {
    "time": 1389357000,
    "kw": 0.15
  },
  {
    "time": 1389357900,
    "kw": 0.14
  },
  {
    "time": 1389358800,
    "kw": 0.14
  },
  {
    "time": 1389359700,
    "kw": 0.24
  },
  {
    "time": 1389360600,
    "kw": 0.51
  },
  {
    "time": 1389361500,
    "kw": 0.94
  },
  {
    "time": 1389362400,
    "kw": 0.96
  },
  {
    "time": 1389363300,
    "kw": 0.95
  },
  {
    "time": 1389364200,
    "kw": 0.96
  },
  {
    "time": 1389365100,
    "kw": 0.96
  },
  {
    "time": 1389366000,
    "kw": 0.93
  },
  {
    "time": 1389366900,
    "kw": 0.93
  },
  {
    "time": 1389367800,
    "kw": 0.95
  },
  {
    "time": 1389368700,
    "kw": 0.93
  },
  {
    "time": 1389369600,
    "kw": 0.97
  },
  {
    "time": 1389370500,
    "kw": 1.25
  },
  {
    "time": 1389371400,
    "kw": 1.15
  },
  {
    "time": 1389372300,
    "kw": 1.13
  },
  {
    "time": 1389373200,
    "kw": 1.14
  },
  {
    "time": 1389374100,
    "kw": 1.17
  },
  {
    "time": 1389375000,
    "kw": 1.32
  },
  {
    "time": 1389375900,
    "kw": 1.54
  },
  {
    "time": 1389376800,
    "kw": 1.57
  },
  {
    "time": 1389377700,
    "kw": 1.4
  },
  {
    "time": 1389378600,
    "kw": 1.36
  },
  {
    "time": 1389379500,
    "kw": 1.21
  },
  {
    "time": 1389380400,
    "kw": 1.22
  },
  {
    "time": 1389381300,
    "kw": 1.53
  },
  {
    "time": 1389382200,
    "kw": 1.02
  },
  {
    "time": 1389383100,
    "kw": 0.98
  },
  {
    "time": 1389384000,
    "kw": 1.15
  },
  {
    "time": 1389384900,
    "kw": 1.1
  },
  {
    "time": 1389385800,
    "kw": 0.48
  },
  {
    "time": 1389386700,
    "kw": 0.4
  },
  {
    "time": 1389387600,
    "kw": 0.38
  },
  {
    "time": 1389388500,
    "kw": 0.4
  },
  {
    "time": 1389389400,
    "kw": 0.37
  },
  {
    "time": 1389390300,
    "kw": 0.37
  },
  {
    "time": 1389391200,
    "kw": 0.32
  },
  {
    "time": 1389392100,
    "kw": 0.34
  },
  {
    "time": 1389393000,
    "kw": 0.17
  },
  {
    "time": 1389393900,
    "kw": 0.08
  },
  {
    "time": 1389394800,
    "kw": 0.11
  },
  {
    "time": 1389395700,
    "kw": 0.11
  },
  {
    "time": 1389396600,
    "kw": 0.07
  },
  {
    "time": 1389397500,
    "kw": 0.08
  },
  {
    "time": 1389398400,
    "kw": 0.36
  },
  {
    "time": 1389399300,
    "kw": 0.1
  },
  {
    "time": 1389400200,
    "kw": 0.05
  },
  {
    "time": 1389401100,
    "kw": 0.05
  },
  {
    "time": 1389402000,
    "kw": 0.07
  },
  {
    "time": 1389402900,
    "kw": 0.07
  },
  {
    "time": 1389403800,
    "kw": 0.04
  },
  {
    "time": 1389404700,
    "kw": 0.03
  },
  {
    "time": 1389405600,
    "kw": 0.05
  },
  {
    "time": 1389406500,
    "kw": 0.06
  },
  {
    "time": 1389407400,
    "kw": 0.06
  },
  {
    "time": 1389408300,
    "kw": 0.04
  },
  {
    "time": 1389409200,
    "kw": 0.06
  },
  {
    "time": 1389410100,
    "kw": 0.06
  },
  {
    "time": 1389411000,
    "kw": 0.04
  },
  {
    "time": 1389411900,
    "kw": 0.03
  },
  {
    "time": 1389412800,
    "kw": 0.05
  },
  {
    "time": 1389413700,
    "kw": 0.04
  },
  {
    "time": 1389414600,
    "kw": 0.03
  },
  {
    "time": 1389415500,
    "kw": 0.03
  },
  {
    "time": 1389416400,
    "kw": 0.04
  },
  {
    "time": 1389417300,
    "kw": 0.07
  },
  {
    "time": 1389418200,
    "kw": 0.15
  },
  {
    "time": 1389419100,
    "kw": 0.08
  },
  {
    "time": 1389420000,
    "kw": 0.26
  },
  {
    "time": 1389420900,
    "kw": 0.18
  },
  {
    "time": 1389421800,
    "kw": 0.16
  },
  {
    "time": 1389422700,
    "kw": 0.15
  },
  {
    "time": 1389423600,
    "kw": 0.26
  },
  {
    "time": 1389424500,
    "kw": 1
  },
  {
    "time": 1389425400,
    "kw": 0.96
  },
  {
    "time": 1389426300,
    "kw": 0.95
  },
  {
    "time": 1389427200,
    "kw": 0.98
  },
  {
    "time": 1389428100,
    "kw": 0.94
  },
  {
    "time": 1389429000,
    "kw": 0.91
  },
  {
    "time": 1389429900,
    "kw": 0.91
  },
  {
    "time": 1389430800,
    "kw": 0.92
  },
  {
    "time": 1389431700,
    "kw": 0.96
  },
  {
    "time": 1389432600,
    "kw": 0.96
  },
  {
    "time": 1389433500,
    "kw": 0.97
  },
  {
    "time": 1389434400,
    "kw": 0.95
  },
  {
    "time": 1389435300,
    "kw": 0.94
  },
  {
    "time": 1389436200,
    "kw": 0.92
  },
  {
    "time": 1389437100,
    "kw": 0.93
  },
  {
    "time": 1389438000,
    "kw": 0.94
  },
  {
    "time": 1389438900,
    "kw": 0.94
  },
  {
    "time": 1389439800,
    "kw": 0.9
  },
  {
    "time": 1389440700,
    "kw": 0.89
  },
  {
    "time": 1389441600,
    "kw": 0.93
  },
  {
    "time": 1389442500,
    "kw": 0.66
  },
  {
    "time": 1389443400,
    "kw": 0.85
  },
  {
    "time": 1389444300,
    "kw": 0.87
  },
  {
    "time": 1389445200,
    "kw": 0.82
  },
  {
    "time": 1389446100,
    "kw": 0.82
  },
  {
    "time": 1389447000,
    "kw": 1.05
  },
  {
    "time": 1389447900,
    "kw": 1.15
  },
  {
    "time": 1389448800,
    "kw": 1.16
  },
  {
    "time": 1389449700,
    "kw": 1.12
  },
  {
    "time": 1389450600,
    "kw": 0.96
  },
  {
    "time": 1389451500,
    "kw": 0.96
  },
  {
    "time": 1389452400,
    "kw": 0.96
  },
  {
    "time": 1389453300,
    "kw": 0.93
  },
  {
    "time": 1389454200,
    "kw": 1.11
  },
  {
    "time": 1389455100,
    "kw": 1.22
  },
  {
    "time": 1389456000,
    "kw": 1.16
  },
  {
    "time": 1389456900,
    "kw": 1.17
  },
  {
    "time": 1389457800,
    "kw": 1.16
  },
  {
    "time": 1389458700,
    "kw": 1.14
  },
  {
    "time": 1389459600,
    "kw": 0.93
  },
  {
    "time": 1389460500,
    "kw": 0.94
  },
  {
    "time": 1389461400,
    "kw": 0.94
  },
  {
    "time": 1389462300,
    "kw": 0.94
  },
  {
    "time": 1389463200,
    "kw": 1.02
  },
  {
    "time": 1389464100,
    "kw": 0.92
  },
  {
    "time": 1389465000,
    "kw": 0.94
  },
  {
    "time": 1389465900,
    "kw": 0.96
  },
  {
    "time": 1389466800,
    "kw": 0.32
  },
  {
    "time": 1389467700,
    "kw": 0.43
  },
  {
    "time": 1389468600,
    "kw": 0.34
  },
  {
    "time": 1389469500,
    "kw": 0.18
  },
  {
    "time": 1389470400,
    "kw": 0.21
  },
  {
    "time": 1389471300,
    "kw": 0.2
  },
  {
    "time": 1389472200,
    "kw": 0.15
  },
  {
    "time": 1389473100,
    "kw": 0.16
  },
  {
    "time": 1389474000,
    "kw": 0.15
  },
  {
    "time": 1389474900,
    "kw": 0.15
  },
  {
    "time": 1389475800,
    "kw": 0.31
  },
  {
    "time": 1389476700,
    "kw": 0.42
  },
  {
    "time": 1389477600,
    "kw": 0.29
  },
  {
    "time": 1389478500,
    "kw": 0.3
  },
  {
    "time": 1389479400,
    "kw": 0.3
  },
  {
    "time": 1389480300,
    "kw": 0.3
  },
  {
    "time": 1389481200,
    "kw": 0.3
  },
  {
    "time": 1389482100,
    "kw": 0.31
  },
  {
    "time": 1389483000,
    "kw": 0.23
  },
  {
    "time": 1389483900,
    "kw": 0.07
  },
  {
    "time": 1389484800,
    "kw": 0.08
  },
  {
    "time": 1389485700,
    "kw": 0.11
  },
  {
    "time": 1389486600,
    "kw": 0.09
  },
  {
    "time": 1389487500,
    "kw": 0.07
  },
  {
    "time": 1389488400,
    "kw": 0.07
  },
  {
    "time": 1389489300,
    "kw": 0.09
  },
  {
    "time": 1389490200,
    "kw": 0.08
  },
  {
    "time": 1389491100,
    "kw": 0.07
  },
  {
    "time": 1389492000,
    "kw": 0.07
  },
  {
    "time": 1389492900,
    "kw": 0.07
  },
  {
    "time": 1389493800,
    "kw": 0.07
  },
  {
    "time": 1389494700,
    "kw": 0.08
  },
  {
    "time": 1389495600,
    "kw": 0.06
  },
  {
    "time": 1389496500,
    "kw": 0.09
  },
  {
    "time": 1389497400,
    "kw": 0.1
  },
  {
    "time": 1389498300,
    "kw": 0.08
  },
  {
    "time": 1389499200,
    "kw": 0.09
  },
  {
    "time": 1389500100,
    "kw": 0.1
  },
  {
    "time": 1389501000,
    "kw": 0.08
  },
  {
    "time": 1389501900,
    "kw": 0.08
  },
  {
    "time": 1389502800,
    "kw": 0.2
  },
  {
    "time": 1389503700,
    "kw": 0.1
  },
  {
    "time": 1389504600,
    "kw": 0.09
  },
  {
    "time": 1389505500,
    "kw": 0.08
  },
  {
    "time": 1389506400,
    "kw": 0.17
  },
  {
    "time": 1389507300,
    "kw": 0.14
  },
  {
    "time": 1389508200,
    "kw": 0.11
  },
  {
    "time": 1389509100,
    "kw": 0.12
  },
  {
    "time": 1389510000,
    "kw": 0.11
  },
  {
    "time": 1389510900,
    "kw": 0.12
  },
  {
    "time": 1389511800,
    "kw": 0.31
  },
  {
    "time": 1389512700,
    "kw": 1
  },
  {
    "time": 1389513600,
    "kw": 1.04
  },
  {
    "time": 1389514500,
    "kw": 0.98
  },
  {
    "time": 1389515400,
    "kw": 0.96
  },
  {
    "time": 1389516300,
    "kw": 1.16
  },
  {
    "time": 1389517200,
    "kw": 1.22
  },
  {
    "time": 1389518100,
    "kw": 1.19
  },
  {
    "time": 1389519000,
    "kw": 1.16
  },
  {
    "time": 1389519900,
    "kw": 0.95
  },
  {
    "time": 1389520800,
    "kw": 0.97
  },
  {
    "time": 1389521700,
    "kw": 0.95
  },
  {
    "time": 1389522600,
    "kw": 0.96
  },
  {
    "time": 1389523500,
    "kw": 0.96
  },
  {
    "time": 1389524400,
    "kw": 0.96
  },
  {
    "time": 1389525300,
    "kw": 1.07
  },
  {
    "time": 1389526200,
    "kw": 1.11
  },
  {
    "time": 1389527100,
    "kw": 0.97
  },
  {
    "time": 1389528000,
    "kw": 0.96
  },
  {
    "time": 1389528900,
    "kw": 0.54
  },
  {
    "time": 1389529800,
    "kw": 0.19
  },
  {
    "time": 1389530700,
    "kw": 0.19
  },
  {
    "time": 1389531600,
    "kw": 0.15
  },
  {
    "time": 1389532500,
    "kw": 0.16
  },
  {
    "time": 1389533400,
    "kw": 0.6
  },
  {
    "time": 1389534300,
    "kw": 1.45
  },
  {
    "time": 1389535200,
    "kw": 1.3
  },
  {
    "time": 1389536100,
    "kw": 1.37
  },
  {
    "time": 1389537000,
    "kw": 1.08
  },
  {
    "time": 1389537900,
    "kw": 1.45
  },
  {
    "time": 1389538800,
    "kw": 1.22
  },
  {
    "time": 1389539700,
    "kw": 1.04
  },
  {
    "time": 1389540600,
    "kw": 1.03
  },
  {
    "time": 1389541500,
    "kw": 1.04
  },
  {
    "time": 1389542400,
    "kw": 1.02
  },
  {
    "time": 1389543300,
    "kw": 0.96
  },
  {
    "time": 1389544200,
    "kw": 0.95
  },
  {
    "time": 1389545100,
    "kw": 0.95
  },
  {
    "time": 1389546000,
    "kw": 0.97
  },
  {
    "time": 1389546900,
    "kw": 0.96
  },
  {
    "time": 1389547800,
    "kw": 1.03
  },
  {
    "time": 1389548700,
    "kw": 0.96
  },
  {
    "time": 1389549600,
    "kw": 0.92
  },
  {
    "time": 1389550500,
    "kw": 0.98
  },
  {
    "time": 1389551400,
    "kw": 0.94
  },
  {
    "time": 1389552300,
    "kw": 0.41
  },
  {
    "time": 1389553200,
    "kw": 0.14
  },
  {
    "time": 1389554100,
    "kw": 0.15
  },
  {
    "time": 1389555000,
    "kw": 0.14
  },
  {
    "time": 1389555900,
    "kw": 0.12
  },
  {
    "time": 1389556800,
    "kw": 0.21
  },
  {
    "time": 1389557700,
    "kw": 0.15
  },
  {
    "time": 1389558600,
    "kw": 0.14
  },
  {
    "time": 1389559500,
    "kw": 0.16
  },
  {
    "time": 1389560400,
    "kw": 0.18
  },
  {
    "time": 1389561300,
    "kw": 0.17
  },
  {
    "time": 1389562200,
    "kw": 0.15
  },
  {
    "time": 1389563100,
    "kw": 0.14
  },
  {
    "time": 1389564000,
    "kw": 0.09
  },
  {
    "time": 1389564900,
    "kw": 0.07
  },
  {
    "time": 1389565800,
    "kw": 0.06
  },
  {
    "time": 1389566700,
    "kw": 0.07
  },
  {
    "time": 1389567600,
    "kw": 0.09
  },
  {
    "time": 1389568500,
    "kw": 0.1
  },
  {
    "time": 1389569400,
    "kw": 0.08
  },
  {
    "time": 1389570300,
    "kw": 0.35
  },
  {
    "time": 1389571200,
    "kw": 0.36
  },
  {
    "time": 1389572100,
    "kw": 0.31
  },
  {
    "time": 1389573000,
    "kw": 0.31
  },
  {
    "time": 1389573900,
    "kw": 0.28
  },
  {
    "time": 1389574800,
    "kw": 0.3
  },
  {
    "time": 1389575700,
    "kw": 0.3
  },
  {
    "time": 1389576600,
    "kw": 0.28
  },
  {
    "time": 1389577500,
    "kw": 0.3
  },
  {
    "time": 1389578400,
    "kw": 0.3
  },
  {
    "time": 1389579300,
    "kw": 0.17
  },
  {
    "time": 1389580200,
    "kw": 0.06
  },
  {
    "time": 1389581100,
    "kw": 0.08
  },
  {
    "time": 1389582000,
    "kw": 0.1
  },
  {
    "time": 1389582900,
    "kw": 0.08
  },
  {
    "time": 1389583800,
    "kw": 0.07
  },
  {
    "time": 1389584700,
    "kw": 0.07
  },
  {
    "time": 1389585600,
    "kw": 0.06
  },
  {
    "time": 1389586500,
    "kw": 0.05
  },
  {
    "time": 1389587400,
    "kw": 0.06
  },
  {
    "time": 1389588300,
    "kw": 0.05
  },
  {
    "time": 1389589200,
    "kw": 0.06
  },
  {
    "time": 1389590100,
    "kw": 0.06
  },
  {
    "time": 1389591000,
    "kw": 0.04
  },
  {
    "time": 1389591900,
    "kw": 0.07
  },
  {
    "time": 1389592800,
    "kw": 0.15
  },
  {
    "time": 1389593700,
    "kw": 0.13
  },
  {
    "time": 1389594600,
    "kw": 0.13
  },
  {
    "time": 1389595500,
    "kw": 0.14
  },
  {
    "time": 1389596400,
    "kw": 0.15
  },
  {
    "time": 1389597300,
    "kw": 0.15
  },
  {
    "time": 1389598200,
    "kw": 0.52
  },
  {
    "time": 1389599100,
    "kw": 0.98
  },
  {
    "time": 1389600000,
    "kw": 1.08
  },
  {
    "time": 1389600900,
    "kw": 0.97
  },
  {
    "time": 1389601800,
    "kw": 0.99
  },
  {
    "time": 1389602700,
    "kw": 0.96
  },
  {
    "time": 1389603600,
    "kw": 1.1
  },
  {
    "time": 1389604500,
    "kw": 1.18
  },
  {
    "time": 1389605400,
    "kw": 0.93
  },
  {
    "time": 1389606300,
    "kw": 0.94
  },
  {
    "time": 1389607200,
    "kw": 0.97
  },
  {
    "time": 1389608100,
    "kw": 1.04
  },
  {
    "time": 1389609000,
    "kw": 0.95
  },
  {
    "time": 1389609900,
    "kw": 0.96
  },
  {
    "time": 1389610800,
    "kw": 0.97
  },
  {
    "time": 1389611700,
    "kw": 0.97
  },
  {
    "time": 1389612600,
    "kw": 0.94
  },
  {
    "time": 1389613500,
    "kw": 0.94
  },
  {
    "time": 1389614400,
    "kw": 0.98
  },
  {
    "time": 1389615300,
    "kw": 1.24
  },
  {
    "time": 1389616200,
    "kw": 1.12
  },
  {
    "time": 1389617100,
    "kw": 1.27
  },
  {
    "time": 1389618000,
    "kw": 1.05
  },
  {
    "time": 1389618900,
    "kw": 0.97
  },
  {
    "time": 1389619800,
    "kw": 1.07
  },
  {
    "time": 1389620700,
    "kw": 0.95
  },
  {
    "time": 1389621600,
    "kw": 0.96
  },
  {
    "time": 1389622500,
    "kw": 0.94
  },
  {
    "time": 1389623400,
    "kw": 0.94
  },
  {
    "time": 1389624300,
    "kw": 0.95
  },
  {
    "time": 1389625200,
    "kw": 0.97
  },
  {
    "time": 1389626100,
    "kw": 0.94
  },
  {
    "time": 1389627000,
    "kw": 0.97
  },
  {
    "time": 1389627900,
    "kw": 1.01
  },
  {
    "time": 1389628800,
    "kw": 0.95
  },
  {
    "time": 1389629700,
    "kw": 0.93
  },
  {
    "time": 1389630600,
    "kw": 0.32
  },
  {
    "time": 1389631500,
    "kw": 0.14
  },
  {
    "time": 1389632400,
    "kw": 0.17
  },
  {
    "time": 1389633300,
    "kw": 0.2
  },
  {
    "time": 1389634200,
    "kw": 0.23
  },
  {
    "time": 1389635100,
    "kw": 0.19
  },
  {
    "time": 1389636000,
    "kw": 0.18
  },
  {
    "time": 1389636900,
    "kw": 0.39
  },
  {
    "time": 1389637800,
    "kw": 0.3
  },
  {
    "time": 1389638700,
    "kw": 0.15
  },
  {
    "time": 1389639600,
    "kw": 0.23
  },
  {
    "time": 1389640500,
    "kw": 0.76
  },
  {
    "time": 1389641400,
    "kw": 0.44
  },
  {
    "time": 1389642300,
    "kw": 0.39
  },
  {
    "time": 1389643200,
    "kw": 0.38
  },
  {
    "time": 1389644100,
    "kw": 0.34
  },
  {
    "time": 1389645000,
    "kw": 0.35
  },
  {
    "time": 1389645900,
    "kw": 0.35
  },
  {
    "time": 1389646800,
    "kw": 0.35
  },
  {
    "time": 1389647700,
    "kw": 0.3
  },
  {
    "time": 1389648600,
    "kw": 0.14
  },
  {
    "time": 1389649500,
    "kw": 0.14
  },
  {
    "time": 1389650400,
    "kw": 0.09
  },
  {
    "time": 1389651300,
    "kw": 0.06
  },
  {
    "time": 1389652200,
    "kw": 0.04
  },
  {
    "time": 1389653100,
    "kw": 0.06
  },
  {
    "time": 1389654000,
    "kw": 0.08
  },
  {
    "time": 1389654900,
    "kw": 0.07
  },
  {
    "time": 1389655800,
    "kw": 0.07
  },
  {
    "time": 1389656700,
    "kw": 0.08
  },
  {
    "time": 1389657600,
    "kw": 0.08
  },
  {
    "time": 1389658500,
    "kw": 0.05
  },
  {
    "time": 1389659400,
    "kw": 0.06
  },
  {
    "time": 1389660300,
    "kw": 0.09
  },
  {
    "time": 1389661200,
    "kw": 0.07
  },
  {
    "time": 1389662100,
    "kw": 0.05
  },
  {
    "time": 1389663000,
    "kw": 0.08
  },
  {
    "time": 1389663900,
    "kw": 0.35
  },
  {
    "time": 1389664800,
    "kw": 0.14
  },
  {
    "time": 1389665700,
    "kw": 0.09
  },
  {
    "time": 1389666600,
    "kw": 0.08
  },
  {
    "time": 1389667500,
    "kw": 0.07
  },
  {
    "time": 1389668400,
    "kw": 0.08
  },
  {
    "time": 1389669300,
    "kw": 0.07
  },
  {
    "time": 1389670200,
    "kw": 0.06
  },
  {
    "time": 1389671100,
    "kw": 0.07
  },
  {
    "time": 1389672000,
    "kw": 0.09
  },
  {
    "time": 1389672900,
    "kw": 0.07
  },
  {
    "time": 1389673800,
    "kw": 0.07
  },
  {
    "time": 1389674700,
    "kw": 0.08
  },
  {
    "time": 1389675600,
    "kw": 0.09
  },
  {
    "time": 1389676500,
    "kw": 0.07
  },
  {
    "time": 1389677400,
    "kw": 0.07
  },
  {
    "time": 1389678300,
    "kw": 0.09
  },
  {
    "time": 1389679200,
    "kw": 0.15
  },
  {
    "time": 1389680100,
    "kw": 0.12
  },
  {
    "time": 1389681000,
    "kw": 0.13
  },
  {
    "time": 1389681900,
    "kw": 0.13
  },
  {
    "time": 1389682800,
    "kw": 0.14
  },
  {
    "time": 1389683700,
    "kw": 0.13
  },
  {
    "time": 1389684600,
    "kw": 0.12
  },
  {
    "time": 1389685500,
    "kw": 0.27
  },
  {
    "time": 1389686400,
    "kw": 0.18
  },
  {
    "time": 1389687300,
    "kw": 0.16
  },
  {
    "time": 1389688200,
    "kw": 0.17
  },
  {
    "time": 1389689100,
    "kw": 0.16
  },
  {
    "time": 1389690000,
    "kw": 0.16
  },
  {
    "time": 1389690900,
    "kw": 0.13
  },
  {
    "time": 1389691800,
    "kw": 0.12
  },
  {
    "time": 1389692700,
    "kw": 0.4
  },
  {
    "time": 1389693600,
    "kw": 0.54
  },
  {
    "time": 1389694500,
    "kw": 0.12
  },
  {
    "time": 1389695400,
    "kw": 0.14
  },
  {
    "time": 1389696300,
    "kw": 0.15
  },
  {
    "time": 1389697200,
    "kw": 0.14
  },
  {
    "time": 1389698100,
    "kw": 0.13
  },
  {
    "time": 1389699000,
    "kw": 0.12
  },
  {
    "time": 1389699900,
    "kw": 0.15
  },
  {
    "time": 1389700800,
    "kw": 0.18
  },
  {
    "time": 1389701700,
    "kw": 0.14
  },
  {
    "time": 1389702600,
    "kw": 0.4
  },
  {
    "time": 1389703500,
    "kw": 0.37
  },
  {
    "time": 1389704400,
    "kw": 0.16
  },
  {
    "time": 1389705300,
    "kw": 0.12
  },
  {
    "time": 1389706200,
    "kw": 0.12
  },
  {
    "time": 1389707100,
    "kw": 0.15
  },
  {
    "time": 1389708000,
    "kw": 0.13
  },
  {
    "time": 1389708900,
    "kw": 0.11
  },
  {
    "time": 1389709800,
    "kw": 0.11
  },
  {
    "time": 1389710700,
    "kw": 0.14
  },
  {
    "time": 1389711600,
    "kw": 0.15
  },
  {
    "time": 1389712500,
    "kw": 0.19
  },
  {
    "time": 1389713400,
    "kw": 0.15
  },
  {
    "time": 1389714300,
    "kw": 0.15
  },
  {
    "time": 1389715200,
    "kw": 0.15
  },
  {
    "time": 1389716100,
    "kw": 0.15
  },
  {
    "time": 1389717000,
    "kw": 0.14
  },
  {
    "time": 1389717900,
    "kw": 0.15
  },
  {
    "time": 1389718800,
    "kw": 0.16
  },
  {
    "time": 1389719700,
    "kw": 0.15
  },
  {
    "time": 1389720600,
    "kw": 0.42
  },
  {
    "time": 1389721500,
    "kw": 0.44
  },
  {
    "time": 1389722400,
    "kw": 0.44
  },
  {
    "time": 1389723300,
    "kw": 0.39
  },
  {
    "time": 1389724200,
    "kw": 0.69
  },
  {
    "time": 1389725100,
    "kw": 0.63
  },
  {
    "time": 1389726000,
    "kw": 0.65
  },
  {
    "time": 1389726900,
    "kw": 0.41
  },
  {
    "time": 1389727800,
    "kw": 0.23
  },
  {
    "time": 1389728700,
    "kw": 0.28
  },
  {
    "time": 1389729600,
    "kw": 0.45
  },
  {
    "time": 1389730500,
    "kw": 0.25
  },
  {
    "time": 1389731400,
    "kw": 0.45
  },
  {
    "time": 1389732300,
    "kw": 0.42
  },
  {
    "time": 1389733200,
    "kw": 0.36
  },
  {
    "time": 1389734100,
    "kw": 0.37
  },
  {
    "time": 1389735000,
    "kw": 0.36
  },
  {
    "time": 1389735900,
    "kw": 0.37
  },
  {
    "time": 1389736800,
    "kw": 0.29
  },
  {
    "time": 1389737700,
    "kw": 0.26
  },
  {
    "time": 1389738600,
    "kw": 0.28
  },
  {
    "time": 1389739500,
    "kw": 0.29
  },
  {
    "time": 1389740400,
    "kw": 0.25
  },
  {
    "time": 1389741300,
    "kw": 0.06
  },
  {
    "time": 1389742200,
    "kw": 0.09
  },
  {
    "time": 1389743100,
    "kw": 0.12
  },
  {
    "time": 1389744000,
    "kw": 0.1
  }
]